edv_data_inspect/edvRegex.py
edv_data_inspect-1.0.2.dist-info/LICENSE
edv_data_inspect-1.0.2.dist-info/METADATA
edv_data_inspect-1.0.2.dist-info/WHEEL
edv_data_inspect-1.0.2.dist-info/entry_points.txt
edv_data_inspect-1.0.2.dist-info/top_level.txt
edv_data_inspect-1.0.2.dist-info/RECORD
