Metadata-Version: 2.1
Name: edv-data-inspect
Version: 1.0.2
Summary: A Python package that helps you to inspect the edv data
Home-page: https://github.com/iamdarshan7/EdvRegex
Author: Darshan Thapa
Author-email: darshanthapa872@gmail.com
License: MIT
Platform: UNKNOWN
Classifier: License :: OSI Approved :: MIT License
Classifier: Programming Language :: Python :: 3
Classifier: Programming Language :: Python :: 3.7
Requires-Dist: pyperclip (==1.8.0)
